easy_logx/__init__.py
easy_logx/easy_logx.py
easy_logx-0.0.3.dist-info/LICENSE
easy_logx-0.0.3.dist-info/METADATA
easy_logx-0.0.3.dist-info/WHEEL
easy_logx-0.0.3.dist-info/top_level.txt
easy_logx-0.0.3.dist-info/RECORD
