Metadata-Version: 2.1
Name: easy-logx
Version: 0.0.3
Summary: A wrapper for python logging
Home-page: UNKNOWN
Author: bug404
Author-email: z19040042@s.upc.edu.cn
License: UNKNOWN
Platform: UNKNOWN
Classifier: Programming Language :: Python :: 3
Classifier: License :: OSI Approved :: MIT License
Classifier: Operating System :: OS Independent
